.gitignore
.gitlab-ci.yml
.gitmodules
AGENTS.md
LICENSE
MANIFEST.in
README.md
cdm_bindings.pyi
heap_monitor.py
requirements.txt
setup.py
test.py
cdm_gui/.gitignore
cdm_gui/__init__.py
cdm_gui/cdm_gui.pyproject
cdm_gui/cdm_gui.pyproject.user
cdm_gui/form.ui
cdm_gui/ui_form.py
cdm_gui/widget.py
common-cdm/cdm_bindings.cpp
common-cdm/frame_decoding.cpp
common-cdm/frame_decoding.hpp
common-cdm/sm_defs.hpp
common-cdm/zmq.hpp
common-cdm/zmq_defs.hpp
common-cdm/common/.clang-format
common-cdm/common/.git
common-cdm/common/.gitlab-ci.yml
common-cdm/common/CMakeLists.txt
common-cdm/common/Kconfig.projbuild
common-cdm/common/README.md
common-cdm/common/adc_frames.hpp
common-cdm/common/aux.hpp
common-cdm/common/cmd.hpp
common-cdm/common/common.kdev4
examples/bsda_ota.py
examples/data_acq.py
examples/data_reader.py
examples/download.py
examples/ebi_ota.py
examples/test_thread.py
integration_tests/test_main.py
pycdm/__init__.py
pycdm/cfg.py
pycdm/cmd_mgr.py
pycdm/comm.py
pycdm/data_mgr.py
pycdm/file_reader.py
pycdm/main.py
pycdm/py.typed
pycdm/structs.py
pycdm/utils.py
virgo_pycdm.egg-info/PKG-INFO
virgo_pycdm.egg-info/SOURCES.txt
virgo_pycdm.egg-info/dependency_links.txt
virgo_pycdm.egg-info/entry_points.txt
virgo_pycdm.egg-info/requires.txt
virgo_pycdm.egg-info/top_level.txt