Metadata-Version: 2.4
Name: virgo-pycdm
Version: 0.4.3
Home-page: https://gitlab.pic.es/virgo-sw/cdm-python-frontend
Author: David Roman
Author-email: droman@ifae.es
License: BSD-3
Platform: any
Classifier: Intended Audience :: Developers
Classifier: License :: OSI Approved :: BSD License
Classifier: Programming Language :: Python :: 3
License-File: LICENSE
Requires-Dist: appdirs
Requires-Dist: PyQt5
Requires-Dist: pybind11
Requires-Dist: pyqt_tools
Requires-Dist: pyzmq
Requires-Dist: tomli
Dynamic: author
Dynamic: author-email
Dynamic: classifier
Dynamic: home-page
Dynamic: license
Dynamic: license-file
Dynamic: platform
Dynamic: requires-dist
